location_profile_local/__init__.py
location_profile_local/constants_location_profile.py
location_profile_local/location_profile.py
location_profile_local-0.0.53.dist-info/METADATA
location_profile_local-0.0.53.dist-info/WHEEL
location_profile_local-0.0.53.dist-info/top_level.txt
location_profile_local-0.0.53.dist-info/RECORD
